hcft/__init__.py
hcft/about_tool.py
hcft/api.py
hcft/hcft.py
hcft/version.py
hcft/helper_classes/__init__.py
hcft/helper_classes/columns_average.py
hcft/helper_classes/csv_tools.py
hcft/helper_classes/files_tools.py
hcft/helper_classes/plot_filtering_settings.py
hcft/utils/__init__.py
hcft/utils/csv_joiner.py
hcft/utils/mpl_figure_editor_qt.py
hcft/view/__init__.py
hcft/view/hcft_view.py
hcft/view/hcft_view_handler.py
hcft-1.0.2.dist-info/LICENSE
hcft-1.0.2.dist-info/METADATA
hcft-1.0.2.dist-info/WHEEL
hcft-1.0.2.dist-info/top_level.txt
hcft-1.0.2.dist-info/RECORD
