Metadata-Version: 2.1
Name: hcft
Version: 1.0.2
Summary: High Cycle Fatigue Tool.
Home-page: https://github.com/bmcs-group/high_cycle_fatigue
Author: H. Spartali & BMCS-Group
Author-email: hspartali@imb.rwt-aachen.de
License: MIT
Platform: UNKNOWN
Classifier: License :: OSI Approved :: MIT License
Classifier: Programming Language :: Python
Classifier: Programming Language :: Python :: 3
Classifier: Programming Language :: Python :: 3.6
Classifier: Programming Language :: Python :: Implementation :: CPython
Classifier: Programming Language :: Python :: Implementation :: PyPy
Requires-Python: >=3.6.0
